{"Lufttemperatur_H": {"date": 1678471200000, "value": "-3.1", "quality": "G", "station": "Linköping-Malmslätt", "distance": 13.258437880726275}, "Vindhastighet": {"date": 1678471200000, "value": "4.0", "quality": "G", "station": "Linköping-Malmslätt", "distance": 13.258437880726275}, "Vindriktning": {"date": 1678471200000, "value": "20", "quality": "G", "station": "Linköping-Malmslätt", "distance": 13.258437880726275}, "Rådande väder": {"date": 1678471200000, "value": "Inget signifikant väder observerat", "quality": "G", "station": "Linköping-Malmslätt", "distance": 13.258437880726275}, "Total molnmängd": {"date": 1678471200000, "value": "100", "quality": "G", "station": "Linköping-Malmslätt", "distance": 13.258437880726275}}